django_log_tracker/__init__.py
django_log_tracker/admin.py
django_log_tracker/apps.py
django_log_tracker/collectstatic.py
django_log_tracker/events.py
django_log_tracker/insert_log_into_database.py
django_log_tracker/models.py
django_log_tracker/start_logger_when_server_starts.py
django_log_tracker/tests.py
django_log_tracker/utils.py
django_log_tracker/views.py
django_log_tracker/middleware/__init__.py
django_log_tracker/middleware/log_tracker_middleware.py
django_log_tracker/migrations/0001_initial.py
django_log_tracker/migrations/__init__.py
django_log_tracker/templates/log_activity_dashboard.html
django_log_tracker-1.0.3.dist-info/LICENSE
django_log_tracker-1.0.3.dist-info/METADATA
django_log_tracker-1.0.3.dist-info/WHEEL
django_log_tracker-1.0.3.dist-info/top_level.txt
django_log_tracker-1.0.3.dist-info/RECORD
